.coveragerc
.pre-commit-config.yaml
.readthedocs.yaml
AUTHORS
Brewfile
CHANGES.rst
LICENSE
MANIFEST.in
README.rst
README_WINDOWS.rst
SECURITY.md
pyproject.toml
setup.py
tox.ini
docs/Makefile
docs/authors.rst
docs/book.rst
docs/changes.rst
docs/conf.py
docs/deployment.rst
docs/development.rst
docs/faq.rst
docs/global.rst.inc
docs/index.rst
docs/installation.rst
docs/internals.rst
docs/introduction.rst
docs/man_intro.rst
docs/quickstart.rst
docs/quickstart_example.rst.inc
docs/support.rst
docs/usage.rst
docs/usage_general.rst.inc
docs/_static/Makefile
docs/_static/favicon.ico
docs/_static/logo.pdf
docs/_static/logo.png
docs/_static/logo.svg
docs/_static/logo_font.txt
docs/_templates/globaltoc.html
docs/_templates/layout.html
docs/_templates/logo-text.html
docs/binaries/00_README.txt
docs/borg_theme/css/borg.css
docs/deployment/automated-local.rst
docs/deployment/central-backup-server.rst
docs/deployment/hosting-repositories.rst
docs/deployment/image-backup.rst
docs/deployment/non-root-user.rst
docs/deployment/pull-backup.rst
docs/internals/compaction.png
docs/internals/compaction.vsd
docs/internals/data-structures.rst
docs/internals/encryption.png
docs/internals/encryption.vsd
docs/internals/frontends.rst
docs/internals/object-graph.png
docs/internals/object-graph.vsd
docs/internals/security.rst
docs/internals/structure.png
docs/internals/structure.vsd
docs/man/borg-benchmark-crud.1
docs/man/borg-benchmark.1
docs/man/borg-break-lock.1
docs/man/borg-change-passphrase.1
docs/man/borg-check.1
docs/man/borg-common.1
docs/man/borg-compact.1
docs/man/borg-compression.1
docs/man/borg-config.1
docs/man/borg-create.1
docs/man/borg-delete.1
docs/man/borg-diff.1
docs/man/borg-export-tar.1
docs/man/borg-extract.1
docs/man/borg-import-tar.1
docs/man/borg-info.1
docs/man/borg-init.1
docs/man/borg-key-change-passphrase.1
docs/man/borg-key-export.1
docs/man/borg-key-import.1
docs/man/borg-key-migrate-to-repokey.1
docs/man/borg-key.1
docs/man/borg-list.1
docs/man/borg-mount.1
src/borgbackup.egg-info/PKG-INFO
src/borgbackup.egg-info/SOURCES.txt
src/borgbackup.egg-info/dependency_links.txt
src/borgbackup.egg-info/entry_points.txt
src/borgbackup.egg-info/requires.txt
src/borgbackup.egg-info/top_level.txt