Metadata-Version: 2.4
Name: borgbackup
Version: 1.4.1
Summary: Deduplicated, encrypted, authenticated and compressed backups
Author: The Borg Collective (see AUTHORS file)
Maintainer-email: Thomas Waldmann <tw@waldmann-edv.de>
License: BSD
Project-URL: Homepage, https://borgbackup.org/
Project-URL: Bug Tracker, https://github.com/borgbackup/borg/issues
Project-URL: Documentation, https://borgbackup.readthedocs.io/
Project-URL: Repository, https://github.com/borgbackup/borg
Project-URL: Changelog, https://github.com/borgbackup/borg/blob/1.4-maint/docs/changes.rst
Keywords: backup,borgbackup
Classifier: Development Status :: 4 - Beta
Classifier: Environment :: Console
Classifier: Intended Audience :: System Administrators
Classifier: License :: OSI Approved :: BSD License
Classifier: Operating System :: POSIX :: BSD :: FreeBSD
Classifier: Operating System :: POSIX :: BSD :: OpenBSD
Classifier: Operating System :: POSIX :: BSD :: NetBSD
Classifier: Operating System :: MacOS :: MacOS X
Classifier: Operating System :: POSIX :: Linux
Classifier: Programming Language :: Python
Classifier: Programming Language :: Python :: 3
Classifier: Programming Language :: Python :: 3.9
Classifier: Programming Language :: Python :: 3.10
Classifier: Programming Language :: Python :: 3.11
Classifier: Programming Language :: Python :: 3.12
Classifier: Programming Language :: Python :: 3.13
Classifier: Topic :: Security :: Cryptography
Classifier: Topic :: System :: Archiving :: Backup
Requires-Python: >=3.9
License-File: LICENSE
License-File: AUTHORS
Requires-Dist: msgpack<=1.1.0,>=1.0.3
Requires-Dist: packaging
Provides-Extra: llfuse
Requires-Dist: llfuse>=1.3.8; extra == "llfuse"
Provides-Extra: pyfuse3
Requires-Dist: pyfuse3>=3.1.1; extra == "pyfuse3"
Provides-Extra: nofuse
Dynamic: description
Dynamic: license-file
